aiopubsub/__init__.py
aiopubsub/constant.py
aiopubsub/decorators.py
aiopubsub/serializer.py
aiopubsub/types.py
aiopubsub/backend/__init__.py
aiopubsub/backend/base.py
aiopubsub/backend/redis_.py
aiopubsub/pubsub/__init__.py
aiopubsub/pubsub/base.py
aiopubsub/pubsub/redis_.py
aiopubsub_py3-1.0.9.dist-info/LICENSE
aiopubsub_py3-1.0.9.dist-info/METADATA
aiopubsub_py3-1.0.9.dist-info/WHEEL
aiopubsub_py3-1.0.9.dist-info/top_level.txt
aiopubsub_py3-1.0.9.dist-info/RECORD
