Metadata-Version: 2.1
Name: aiopubsub-py3
Version: 1.0.9
Summary: aio pubsub 
Home-page: https://github.com/daleeg/aio_pubsub
License: MIT
Keywords: aio redis pubsub mqtt publish subscribe
Platform: POSIX
Classifier: License :: OSI Approved :: MIT License
Classifier: Development Status :: 5 - Production/Stable
Classifier: Programming Language :: Python
Classifier: Programming Language :: Python :: 3
Classifier: Programming Language :: Python :: 3.6
Classifier: Programming Language :: Python :: 3.7
Classifier: Programming Language :: Python :: 3.8
Classifier: Programming Language :: Python :: 3.9
Classifier: Programming Language :: Python :: 3.10
Classifier: Programming Language :: Python :: 3.11
Classifier: Programming Language :: Python :: 3.12
Classifier: Programming Language :: Python :: 3 :: Only
Classifier: Operating System :: POSIX
Classifier: Environment :: Web Environment
Classifier: Intended Audience :: Developers
Classifier: Topic :: Software Development
Classifier: Topic :: Software Development :: Libraries
Classifier: Framework :: AsyncIO
Requires-Python: >=3.8
License-File: LICENSE
Provides-Extra: redis_
Requires-Dist: redis (>=5.0.1) ; extra == 'redis_'
